ircparse.py
ircparse-0.1.0.dist-info/WHEEL
ircparse-0.1.0.dist-info/METADATA
ircparse-0.1.0.dist-info/RECORD
