Metadata-Version: 2.1
Name: ircparse
Version: 0.1.0
Summary: IRC parsing utilities
License: MIT
Author: Andrew Herbig
Author-email: notandrewherbig@gmail.com
Requires-Python: >=3.7,<4.0
Classifier: License :: OSI Approved :: MIT License
Classifier: Programming Language :: Python :: 3
Classifier: Programming Language :: Python :: 3.7
Classifier: Programming Language :: Python :: 3.8
Requires-Dist: pydantic (>=1.6.1,<2.0.0)
